calculate/__init__.py
calculate/calc.py
calculate/unit_tests.py
eliran_calculator-0.0.1.dist-info/METADATA
eliran_calculator-0.0.1.dist-info/WHEEL
eliran_calculator-0.0.1.dist-info/top_level.txt
eliran_calculator-0.0.1.dist-info/RECORD
