Metadata-Version: 2.1
Name: eliran-calculator
Version: 0.0.1
Summary: This is a Test Package
Home-page: UNKNOWN
License: UNKNOWN
Platform: UNKNOWN
Requires-Dist: wheel (>=0.37.1)
